{
    "key": "B",
    "suffix": "7sus2/A#",
    "positions": [
        {
            "frets": "6x7677",
            "fingers": "102134",
            "barres": "6",
            "capo": "true"
        },
        {
            "frets": "647x77",
            "fingers": "314044",
            "barres": "7",
            "capo": "true"
        },
        {
            "frets": "64747x",
            "fingers": "213140",
            "barres": "4",
            "capo": "true"
        },
        {
            "frets": "644475",
            "fingers": "311142",
            "barres": "4",
            "capo": "true"
        },
        {
            "frets": "6474x7",
            "fingers": "213104",
            "barres": "4",
            "capo": "true"
        },
        {
            "frets": "6474x5",
            "fingers": "314102",
            "barres": "4",
            "capo": "true"
        },
        {
            "frets": "6976x7",
            "fingers": "142103",
            "barres": "6",
            "capo": "true"
        },
        {
            "frets": "ixjijj",
            "fingers": "102134",
            "barres": "18",
            "capo": "true"
        },
        {
            "frets": "igjxjj",
            "fingers": "314044",
            "barres": "19",
            "capo": "true"
        },
        {
            "frets": "igggjh",
            "fingers": "311142",
            "barres": "16",
            "capo": "true"
        },
        {
            "frets": "igjgjx",
            "fingers": "213140",
            "barres": "16",
            "capo": "true"
        },
        {
            "frets": "xdbecx",
            "fingers": "031420"
        },
        {
            "frets": "igjgxj",
            "fingers": "213104",
            "barres": "16",
            "capo": "true"
        },
        {
            "frets": "igjgxh",
            "fingers": "314102",
            "barres": "16",
            "capo": "true"
        },
        {
            "frets": "iljixj",
            "fingers": "142103",
            "barres": "18",
            "capo": "true"
        }
    ]
}