{
    "key": "E",
    "suffix": "maj7sus2sus4/F#",
    "positions": [
        {
            "frets": "201200",
            "fingers": "201300"
        },
        {
            "frets": "221200",
            "fingers": "231400"
        },
        {
            "frets": "x999ab",
            "fingers": "011123",
            "barres": "9",
            "capo": "true"
        },
        {
            "frets": "eeeege",
            "fingers": "111131",
            "barres": "14",
            "capo": "true"
        },
        {
            "frets": "ecdecc",
            "fingers": "312411",
            "barres": "12",
            "capo": "true"
        },
        {
            "frets": "eeeegh",
            "fingers": "111134",
            "barres": "14",
            "capo": "true"
        },
        {
            "frets": "ecebxb",
            "fingers": "324101",
            "barres": "11",
            "capo": "true"
        },
        {
            "frets": "exeexb",
            "fingers": "203401"
        }
    ]
}