{
    "key": "F",
    "suffix": "maj7sus4#5/B",
    "positions": [
        {
            "frets": "x23320",
            "fingers": "013420"
        },
        {
            "frets": "778666",
            "fingers": "234111",
            "barres": "6",
            "capo": "true"
        },
        {
            "frets": "778ax9",
            "fingers": "112403",
            "barres": "7",
            "capo": "true"
        },
        {
            "frets": "jjkiii",
            "fingers": "234111",
            "barres": "18",
            "capo": "true"
        },
        {
            "frets": "jjkmxl",
            "fingers": "112403",
            "barres": "19",
            "capo": "true"
        }
    ]
}