{
    "key": "C#",
    "suffix": "m7/E",
    "positions": [
        {
            "frets": "022120",
            "fingers": "023140"
        },
        {
            "frets": "xx2424",
            "fingers": "001324"
        },
        {
            "frets": "x79999",
            "fingers": "013334",
            "barres": "9",
            "capo": "true"
        },
        {
            "frets": "cb9999",
            "fingers": "431111",
            "barres": "9",
            "capo": "true"
        },
        {
            "frets": "cb99c9",
            "fingers": "321141",
            "barres": "9",
            "capo": "true"
        },
        {
            "frets": "cbbxcc",
            "fingers": "211034",
            "barres": "11",
            "capo": "true"
        },
        {
            "frets": "x76697",
            "fingers": "021143",
            "barres": "6",
            "capo": "true"
        },
        {
            "frets": "x7x657",
            "fingers": "030214"
        },
        {
            "frets": "ceexec",
            "fingers": "123041",
            "barres": "12",
            "capo": "true"
        },
        {
            "frets": "cbbdcx",
            "fingers": "211430",
            "barres": "11",
            "capo": "true"
        },
        {
            "frets": "x7969x",
            "fingers": "023140"
        },
        {
            "frets": "cxb9c9",
            "fingers": "302141",
            "barres": "9",
            "capo": "true"
        },
        {
            "frets": "cexdec",
            "fingers": "130241",
            "barres": "12",
            "capo": "true"
        },
        {
            "frets": "x796x9",
            "fingers": "023104"
        },
        {
            "frets": "xjllll",
            "fingers": "013334",
            "barres": "21",
            "capo": "true"
        },
        {
            "frets": "x796x7",
            "fingers": "024103"
        },
        {
            "frets": "xxegeg",
            "fingers": "001324"
        },
        {
            "frets": "cebdxx",
            "fingers": "241300"
        },
        {
            "frets": "cebxex",
            "fingers": "231040"
        },
        {
            "frets": "xjiilj",
            "fingers": "021143",
            "barres": "18",
            "capo": "true"
        },
        {
            "frets": "cebxcx",
            "fingers": "241030"
        },
        {
            "frets": "cebxxc",
            "fingers": "241003"
        },
        {
            "frets": "xjxihj",
            "fingers": "030214"
        },
        {
            "frets": "xjlilx",
            "fingers": "023140"
        },
        {
            "frets": "xjlixl",
            "fingers": "023104"
        },
        {
            "frets": "xjlixj",
            "fingers": "024103"
        }
    ]
}