{
    "key": "G",
    "suffix": "9b5/B",
    "positions": [
        {
            "frets": "7x5665",
            "fingers": "401231",
            "barres": "5",
            "capo": "true"
        },
        {
            "frets": "7856x5",
            "fingers": "341201",
            "barres": "5",
            "capo": "true"
        },
        {
            "frets": "jxhiih",
            "fingers": "401231",
            "barres": "17",
            "capo": "true"
        },
        {
            "frets": "jkhixh",
            "fingers": "341201",
            "barres": "17",
            "capo": "true"
        }
    ]
}